{
  "ticker": "HL",
  "source": "yahoo",
  "firstDate": "1980-03-17",
  "lastDate": "2026-07-17",
  "records": 11676,
  "backfillCompleted": true,
  "adjustedSeriesValidated": true,
  "lastCorporateActionDate": "2026-05-22",
  "lastSplitDate": "1981-03-25",
  "corporateActionHash": "sha256:6ce2c511a1c61a0170be2bc5530306055a4f7e430b8ff1dd66fa3b864f229bf0",
  "priceDataHash": "sha256:94f09f1149cad77d8b5ed5fe1c86f8dc181f2c16e52b1efdf58a9d724202871a",
  "lastFullValidationAt": "2026-07-14T16:29:16Z",
  "updatedAt": "2026-07-18T07:08:25Z"
}
