{
  "ticker": "ALNY",
  "source": "yahoo",
  "firstDate": "2004-06-01",
  "lastDate": "2026-07-16",
  "records": 5566,
  "backfillCompleted": true,
  "adjustedSeriesValidated": true,
  "lastCorporateActionDate": "",
  "lastSplitDate": "",
  "corporateActionHash": "sha256:e3b0c44298fc1c149afbf4c8996fb92427ae41e4649b934ca495991b7852b855",
  "priceDataHash": "sha256:d7a69aa5805bb91a8022b252579f98eb96f0b7d2f524c294fd6e2e95e35da581",
  "lastFullValidationAt": "2026-07-14T15:03:29Z",
  "updatedAt": "2026-07-17T04:13:21Z"
}
