{
  "ticker": "WDFC",
  "source": "yahoo",
  "firstDate": "1973-05-03",
  "lastDate": "2026-07-22",
  "records": 13158,
  "backfillCompleted": true,
  "adjustedSeriesValidated": true,
  "lastCorporateActionDate": "2026-07-17",
  "lastSplitDate": "1997-08-01",
  "corporateActionHash": "sha256:577241ff2a51dbff3d332e51fd0cff668d029986565ef45ed33f33a7092c1dce",
  "priceDataHash": "sha256:33d128ec619ff06021b2699c7e9624e3c5271ad744abba4133faf05d52ab01a7",
  "lastFullValidationAt": "2026-07-23T15:45:43Z",
  "updatedAt": "2026-07-23T15:45:43Z"
}
