{
  "ticker": "NWS",
  "source": "yahoo",
  "firstDate": "2013-06-19",
  "lastDate": "2026-07-23",
  "records": 3293,
  "backfillCompleted": true,
  "adjustedSeriesValidated": true,
  "lastCorporateActionDate": "2026-03-11",
  "lastSplitDate": "",
  "corporateActionHash": "sha256:f45e93c2a4286926d28e4ef5ddec97da3277a12dd7a7e8d6e25747ec0a7c1582",
  "priceDataHash": "sha256:db448fa83f67b3419893a88539f9dabc38a75de7a7f7f6c6a78e532afdf66108",
  "lastFullValidationAt": "2026-07-23T15:13:53Z",
  "updatedAt": "2026-07-24T16:53:41Z"
}
