{
  "ticker": "FSLR",
  "source": "yahoo",
  "firstDate": "2006-11-17",
  "lastDate": "2026-07-09",
  "records": 4938,
  "backfillCompleted": true,
  "adjustedSeriesValidated": true,
  "lastCorporateActionDate": "",
  "lastSplitDate": "",
  "corporateActionHash": "sha256:e3b0c44298fc1c149afbf4c8996fb92427ae41e4649b934ca495991b7852b855",
  "priceDataHash": "sha256:98d0b6c6e2bf4406e350a8af539071f1f1eeb434014d575aa4ae2d620af7af82",
  "lastFullValidationAt": "2026-07-07T13:34:19Z",
  "updatedAt": "2026-07-10T08:27:48Z"
}
