{
  "ticker": "FCF",
  "source": "yahoo",
  "firstDate": "1992-06-10",
  "lastDate": "2026-07-15",
  "records": 8495,
  "backfillCompleted": true,
  "adjustedSeriesValidated": true,
  "lastCorporateActionDate": "2026-05-08",
  "lastSplitDate": "1999-11-19",
  "corporateActionHash": "sha256:ab8896fdd401f83dc9f26917b0cb31cbabe6927ae838625133b876d3699db27f",
  "priceDataHash": "sha256:f1f6bd4afcab82e86e990b4ceea383fa218afa6792bd4f4356b60ee091be5faa",
  "lastFullValidationAt": "2026-07-14T16:20:40Z",
  "updatedAt": "2026-07-16T07:29:05Z"
}
