{
  "ticker": "BGC",
  "source": "yahoo",
  "firstDate": "1999-12-10",
  "lastDate": "2026-07-10",
  "records": 6671,
  "backfillCompleted": true,
  "adjustedSeriesValidated": true,
  "lastCorporateActionDate": "2026-05-27",
  "lastSplitDate": "2018-12-03",
  "corporateActionHash": "sha256:1bfd8b0ba6f3ee5a070895489fa9ec7e7de61072f4eb0098c641ac7106e7414c",
  "priceDataHash": "sha256:f12a9a6f646bc523516c5fc0320b9d086aa641dae759d56f80056b120f57d2de",
  "lastFullValidationAt": "2026-07-07T13:09:35Z",
  "updatedAt": "2026-07-11T04:22:07Z"
}
