{
  "ticker": "VSXY",
  "source": "yahoo",
  "firstDate": "2021-07-21",
  "lastDate": "2026-07-06",
  "records": 1244,
  "backfillCompleted": true,
  "adjustedSeriesValidated": true,
  "lastCorporateActionDate": "",
  "lastSplitDate": "",
  "corporateActionHash": "sha256:e3b0c44298fc1c149afbf4c8996fb92427ae41e4649b934ca495991b7852b855",
  "priceDataHash": "sha256:1749b48d1e9d1298341d5309b022882a3b8e6f91638488c0f7d33a12644257c7",
  "lastFullValidationAt": "2026-07-07T14:32:27Z",
  "updatedAt": "2026-07-07T14:32:27Z"
}
