{
  "ticker": "SAIA",
  "source": "yahoo",
  "firstDate": "2002-09-11",
  "lastDate": "2026-07-09",
  "records": 5994,
  "backfillCompleted": true,
  "adjustedSeriesValidated": true,
  "lastCorporateActionDate": "2013-06-14",
  "lastSplitDate": "2013-06-14",
  "corporateActionHash": "sha256:fdcd20cfdab9fdb893877665c8710e7d29b34bc072aedf11f43a523b240e66a1",
  "priceDataHash": "sha256:709b971580eb3da196120052cad0ada011bc108aecd3b0f27cbda3def5235622",
  "lastFullValidationAt": "2026-07-07T14:16:27Z",
  "updatedAt": "2026-07-10T12:05:37Z"
}
