{
  "ticker": "LECO",
  "source": "yahoo",
  "firstDate": "1994-04-07",
  "lastDate": "2026-07-10",
  "records": 8001,
  "backfillCompleted": true,
  "adjustedSeriesValidated": true,
  "lastCorporateActionDate": "2026-06-30",
  "lastSplitDate": "2011-06-01",
  "corporateActionHash": "sha256:9f1b10e786e51bafde1737ea1e3cbe3a292710299fbb3a14009419dc4d715883",
  "priceDataHash": "sha256:4ae0957e0f7906624840b7df4c18529e128df37bce29551a5062e9849386accb",
  "lastFullValidationAt": "2026-07-07T13:48:59Z",
  "updatedAt": "2026-07-11T07:26:22Z"
}
