{
  "ticker": "EFX",
  "source": "yahoo",
  "firstDate": "1980-03-17",
  "lastDate": "2026-07-21",
  "records": 11572,
  "backfillCompleted": true,
  "adjustedSeriesValidated": true,
  "lastCorporateActionDate": "2026-05-22",
  "lastSplitDate": "1995-12-18",
  "corporateActionHash": "sha256:18da0744e0d428eb9aca7481c25d6d9dcece1cc095027294466e2c0ee66b156e",
  "priceDataHash": "sha256:0c5c1c40f956780f7fd6462457e5fc87501f790415e15bac4f9a4a8dcf785df5",
  "lastFullValidationAt": "2026-07-22T04:51:30Z",
  "updatedAt": "2026-07-22T04:51:30Z"
}
