{
  "ticker": "SSB",
  "source": "yahoo",
  "firstDate": "1997-01-28",
  "lastDate": "2026-07-15",
  "records": 7197,
  "backfillCompleted": true,
  "adjustedSeriesValidated": true,
  "lastCorporateActionDate": "2026-05-08",
  "lastSplitDate": "2007-03-07",
  "corporateActionHash": "sha256:96a9912cc5e7c388400703291025dc2799e87d59b5474518af68920baec49d50",
  "priceDataHash": "sha256:6168c726bba852b5be0fff236178bae9bbd18f3b8a50f0d8a00096fa57f9b16a",
  "lastFullValidationAt": "2026-07-15T16:48:30Z",
  "updatedAt": "2026-07-16T11:14:11Z"
}
