{
  "ticker": "GRC",
  "source": "yahoo",
  "firstDate": "1980-03-18",
  "lastDate": "2026-07-22",
  "records": 11336,
  "backfillCompleted": true,
  "adjustedSeriesValidated": true,
  "lastCorporateActionDate": "2026-05-15",
  "lastSplitDate": "2013-12-11",
  "corporateActionHash": "sha256:9339adc80f4147475bc044f96173f3bdf146cc661376f5b0d60b6feebf586aae",
  "priceDataHash": "sha256:a0d5d405a41bf6b7ab6e5bf6ca1cc00c6f92b288ce992b3b10b10e4f6f7907e2",
  "lastFullValidationAt": "2026-07-22T11:21:23Z",
  "updatedAt": "2026-07-23T11:18:30Z"
}
