{
  "ticker": "FTAI",
  "source": "yahoo",
  "firstDate": "2015-05-15",
  "lastDate": "2026-07-07",
  "records": 2799,
  "backfillCompleted": true,
  "adjustedSeriesValidated": true,
  "lastCorporateActionDate": "2026-05-13",
  "lastSplitDate": "2022-08-02",
  "corporateActionHash": "sha256:749d380f4cbf813a354e5bba60641e4ee111a9251e1194c48f3710ef73677792",
  "priceDataHash": "sha256:9f91e63f8ecd3c3d1af9c21edcfb39b522abef774500a87dea1c55f91e44ed1f",
  "lastFullValidationAt": "2026-07-07T13:34:31Z",
  "updatedAt": "2026-07-08T07:37:36Z"
}
