{
  "ticker": "EPAM",
  "source": "yahoo",
  "firstDate": "2012-02-08",
  "lastDate": "2026-07-23",
  "records": 3634,
  "backfillCompleted": true,
  "adjustedSeriesValidated": true,
  "lastCorporateActionDate": "",
  "lastSplitDate": "",
  "corporateActionHash": "sha256:e3b0c44298fc1c149afbf4c8996fb92427ae41e4649b934ca495991b7852b855",
  "priceDataHash": "sha256:73c749287edf39a6a2457b13e32b0f146e3c9021c387af82659953ebc7cc853c",
  "lastFullValidationAt": "2026-07-22T04:52:46Z",
  "updatedAt": "2026-07-24T04:37:38Z"
}
