{
  "ticker": "ACI",
  "source": "yahoo",
  "firstDate": "2020-06-26",
  "lastDate": "2026-07-16",
  "records": 1520,
  "backfillCompleted": true,
  "adjustedSeriesValidated": true,
  "lastCorporateActionDate": "2026-04-24",
  "lastSplitDate": "",
  "corporateActionHash": "sha256:d24de38b5f4dd41211ecc53ac55cd50f6a0221a7d6d3ba1fc88aa08ff28e5557",
  "priceDataHash": "sha256:676d27f7568610da72a68893056986684df76918bee091835a2cd39a42f607a0",
  "lastFullValidationAt": "2026-07-14T15:00:04Z",
  "updatedAt": "2026-07-17T04:11:35Z"
}
