{
  "ticker": "SOLV",
  "source": "yahoo",
  "firstDate": "2024-03-26",
  "lastDate": "2026-07-09",
  "records": 573,
  "backfillCompleted": true,
  "adjustedSeriesValidated": true,
  "lastCorporateActionDate": "",
  "lastSplitDate": "",
  "corporateActionHash": "sha256:e3b0c44298fc1c149afbf4c8996fb92427ae41e4649b934ca495991b7852b855",
  "priceDataHash": "sha256:a6a31083e3a232fc2339065a0d454f5e55d90a94d9963639f1bbd81283311edf",
  "lastFullValidationAt": "2026-07-07T14:20:23Z",
  "updatedAt": "2026-07-10T12:07:41Z"
}
