{
  "ticker": "PRMB",
  "source": "yahoo",
  "firstDate": "1992-06-16",
  "lastDate": "2026-07-22",
  "records": 8560,
  "backfillCompleted": true,
  "adjustedSeriesValidated": true,
  "lastCorporateActionDate": "2026-06-04",
  "lastSplitDate": "1993-07-26",
  "corporateActionHash": "sha256:54162fc3e6d79b2ceb816ab5ef42c17781f237aa1cc3d1985706346c4b30c9fd",
  "priceDataHash": "sha256:87f6e9d390e82f2377539972445cfef1e9b70142183257dcbcd9b038414ba1a5",
  "lastFullValidationAt": "2026-07-23T15:21:47Z",
  "updatedAt": "2026-07-23T15:21:47Z"
}
