{
  "ticker": "MHK",
  "source": "yahoo",
  "firstDate": "1992-04-01",
  "lastDate": "2026-07-08",
  "records": 8626,
  "backfillCompleted": true,
  "adjustedSeriesValidated": true,
  "lastCorporateActionDate": "1997-12-05",
  "lastSplitDate": "1997-12-05",
  "corporateActionHash": "sha256:bf8d762452dc10a2b5fa6c821d99749d45dbb245f7d705043ca59e5653686288",
  "priceDataHash": "sha256:1a8be4fc169a4d426e6b436b920b4aabb48fcbdb3bdee12bdaebe8d9ee376c81",
  "lastFullValidationAt": "2026-07-07T13:54:23Z",
  "updatedAt": "2026-07-09T08:43:35Z"
}
