{
  "ticker": "FRT",
  "source": "yahoo",
  "firstDate": "1973-05-03",
  "lastDate": "2026-07-07",
  "records": 12884,
  "backfillCompleted": true,
  "adjustedSeriesValidated": true,
  "lastCorporateActionDate": "2026-07-01",
  "lastSplitDate": "1985-11-06",
  "corporateActionHash": "sha256:1ac5fd06fd0b6080ec9404d8547fc4ff10fd0db6d50ba87a16bbbb44e9c23c75",
  "priceDataHash": "sha256:b4fe1129cbce8914661d4446e5353a1d55630da4c5871ddf096679403fa4f924",
  "lastFullValidationAt": "2026-07-07T13:34:07Z",
  "updatedAt": "2026-07-08T07:37:24Z"
}
