{
  "ticker": "ALRM",
  "source": "yahoo",
  "firstDate": "2015-06-26",
  "lastDate": "2026-07-08",
  "records": 2773,
  "backfillCompleted": true,
  "adjustedSeriesValidated": true,
  "lastCorporateActionDate": "",
  "lastSplitDate": "",
  "corporateActionHash": "sha256:e3b0c44298fc1c149afbf4c8996fb92427ae41e4649b934ca495991b7852b855",
  "priceDataHash": "sha256:2bb6447a646ac880c94f12309076336adcbb6f8b73d33464d99ee22b5260699c",
  "lastFullValidationAt": "2026-07-07T13:02:03Z",
  "updatedAt": "2026-07-09T05:01:51Z"
}
