{
  "ticker": "AIR",
  "source": "yahoo",
  "firstDate": "1980-03-17",
  "lastDate": "2026-07-15",
  "records": 11497,
  "backfillCompleted": true,
  "adjustedSeriesValidated": true,
  "lastCorporateActionDate": "2020-03-27",
  "lastSplitDate": "1998-02-24",
  "corporateActionHash": "sha256:a1300ebcdeb25da6d0f02e2b8a1803e2a845c883255730d21d780804df0e31ab",
  "priceDataHash": "sha256:18e1b094dc27702061d576323a8816d57d7b48c5a1e60b1172432be84e115556",
  "lastFullValidationAt": "2026-07-14T15:02:09Z",
  "updatedAt": "2026-07-16T04:14:18Z"
}
