{
  "ticker": "KEY",
  "source": "yahoo",
  "firstDate": "1987-11-05",
  "lastDate": "2026-07-21",
  "records": 9684,
  "backfillCompleted": true,
  "adjustedSeriesValidated": true,
  "lastCorporateActionDate": "2026-06-02",
  "lastSplitDate": "1998-03-09",
  "corporateActionHash": "sha256:f2d7244f2c3644666f5feb34c46415ef64360609e3a5bc43f0b66f49160cce9e",
  "priceDataHash": "sha256:d299c495ed4bded13cbf8bc74227784632df0929e253e5889ad5ffdd3af95cd7",
  "lastFullValidationAt": "2026-07-22T11:30:19Z",
  "updatedAt": "2026-07-22T11:30:19Z"
}
