{
  "ticker": "SKY",
  "source": "yahoo",
  "firstDate": "1973-05-03",
  "lastDate": "2026-07-08",
  "records": 13225,
  "backfillCompleted": true,
  "adjustedSeriesValidated": true,
  "lastCorporateActionDate": "2018-06-01",
  "lastSplitDate": "",
  "corporateActionHash": "sha256:84f29cfa5d125acf633f2604baab68bc72e9363d773d2286abcb7d1cacb4f45d",
  "priceDataHash": "sha256:15a8fcc44e1f6d7b48da210bbcda2b5bc2cf586bede1e81c03f931f28f091ad1",
  "lastFullValidationAt": "2026-07-07T14:18:44Z",
  "updatedAt": "2026-07-09T12:15:12Z"
}
