{
  "ticker": "MDB",
  "source": "yahoo",
  "firstDate": "2017-10-19",
  "lastDate": "2026-07-10",
  "records": 2191,
  "backfillCompleted": true,
  "adjustedSeriesValidated": true,
  "lastCorporateActionDate": "",
  "lastSplitDate": "",
  "corporateActionHash": "sha256:e3b0c44298fc1c149afbf4c8996fb92427ae41e4649b934ca495991b7852b855",
  "priceDataHash": "sha256:79eedca320326260d0b19869d5e60ceb6c4f5e0a40c54faed53093575e8f10c0",
  "lastFullValidationAt": "2026-07-07T13:53:27Z",
  "updatedAt": "2026-07-11T07:28:36Z"
}
