{
  "ticker": "MNR",
  "source": "yahoo",
  "firstDate": "2023-10-25",
  "lastDate": "2026-07-17",
  "records": 683,
  "backfillCompleted": true,
  "adjustedSeriesValidated": true,
  "lastCorporateActionDate": "2026-05-21",
  "lastSplitDate": "",
  "corporateActionHash": "sha256:351081ad42b3157a226462456be4d3b93bcf5b31578fa4758b8fb35071e0feb5",
  "priceDataHash": "sha256:bacc3b069b7f5f5b2d7ddf224a182df37bd621522af2b4cd44a63690b56f2010",
  "lastFullValidationAt": "2026-07-14T16:44:54Z",
  "updatedAt": "2026-07-18T07:16:33Z"
}
