{
  "ticker": "CMS",
  "source": "yahoo",
  "firstDate": "1973-02-21",
  "lastDate": "2026-07-22",
  "records": 13281,
  "backfillCompleted": true,
  "adjustedSeriesValidated": true,
  "lastCorporateActionDate": "2026-05-08",
  "lastSplitDate": "",
  "corporateActionHash": "sha256:0b2aa939a7ca1a9f835d7b6443f846ced3a3738eb93698aa5b59accd47286b2f",
  "priceDataHash": "sha256:bb177757dc8e8bca4b1b4718cb6bcfcfe71a9e5bc41cc31bc63d83a563cdeae0",
  "lastFullValidationAt": "2026-07-22T04:41:56Z",
  "updatedAt": "2026-07-23T04:32:37Z"
}
