{
  "ticker": "LNTH",
  "source": "yahoo",
  "firstDate": "2015-06-25",
  "lastDate": "2026-07-20",
  "records": 2782,
  "backfillCompleted": true,
  "adjustedSeriesValidated": true,
  "lastCorporateActionDate": "",
  "lastSplitDate": "",
  "corporateActionHash": "sha256:e3b0c44298fc1c149afbf4c8996fb92427ae41e4649b934ca495991b7852b855",
  "priceDataHash": "sha256:df76d898c1953e558e278e737795c40e029c3e6e9507e522b1d598c4ed0aef52",
  "lastFullValidationAt": "2026-07-14T16:40:04Z",
  "updatedAt": "2026-07-21T11:24:17Z"
}
