{
  "ticker": "DHI",
  "source": "yahoo",
  "firstDate": "1992-06-05",
  "lastDate": "2026-07-22",
  "records": 8510,
  "backfillCompleted": true,
  "adjustedSeriesValidated": true,
  "lastCorporateActionDate": "2026-05-07",
  "lastSplitDate": "2005-03-17",
  "corporateActionHash": "sha256:7b0874c812b79fe291c1bf827484fc940e6f226ad093aa6ea8b70f6577c600ee",
  "priceDataHash": "sha256:58fd33c8c7096b88f69efb33b18bd5c5bfd398179a86d208dcbb333745dbf386",
  "lastFullValidationAt": "2026-07-22T04:48:22Z",
  "updatedAt": "2026-07-23T04:35:50Z"
}
