{
  "ticker": "BWA",
  "source": "yahoo",
  "firstDate": "1993-08-13",
  "lastDate": "2026-07-22",
  "records": 8246,
  "backfillCompleted": true,
  "adjustedSeriesValidated": true,
  "lastCorporateActionDate": "2026-06-01",
  "lastSplitDate": "2023-07-05",
  "corporateActionHash": "sha256:acf1e70e98165e3a6a9b92ec741490a58ae80f9c3a45bd57b37b4aa4ff3d1e95",
  "priceDataHash": "sha256:6184e0d429cd0e1a0e2a20d72e6d53e015362fcaef0544a401e2aff2c84abcb2",
  "lastFullValidationAt": "2026-07-22T04:36:44Z",
  "updatedAt": "2026-07-23T04:29:58Z"
}
