{
  "ticker": "RTX",
  "source": "yahoo",
  "firstDate": "1962-04-02",
  "lastDate": "2026-07-14",
  "records": 16023,
  "backfillCompleted": true,
  "adjustedSeriesValidated": true,
  "lastCorporateActionDate": "2026-05-22",
  "lastSplitDate": "2020-04-03",
  "corporateActionHash": "sha256:2a69f3c7f4e79b1bb76891ccf8b6c6a06ff5fb4573f5d937577ee83bdf16a70e",
  "priceDataHash": "sha256:22271003b53a741093f21d8f3055b5101238cdbdd2365fa9068b14196f900d29",
  "lastFullValidationAt": "2026-07-15T16:42:34Z",
  "updatedAt": "2026-07-15T16:42:34Z"
}
