{
  "ticker": "MSCI",
  "source": "yahoo",
  "firstDate": "2007-11-15",
  "lastDate": "2026-07-22",
  "records": 4695,
  "backfillCompleted": true,
  "adjustedSeriesValidated": true,
  "lastCorporateActionDate": "2026-05-15",
  "lastSplitDate": "",
  "corporateActionHash": "sha256:abffed901a49b9d87a11bdcb56006fc5ac0e0078e7d62c825fc4be4db3a506e5",
  "priceDataHash": "sha256:2f7fde41f49b079b05ae834e99b0b51b614d8e3fb81a6445af67b385030a363a",
  "lastFullValidationAt": "2026-07-22T11:40:43Z",
  "updatedAt": "2026-07-23T11:28:32Z"
}
