{
  "ticker": "GATX",
  "source": "yahoo",
  "firstDate": "1973-02-21",
  "lastDate": "2026-07-13",
  "records": 13335,
  "backfillCompleted": true,
  "adjustedSeriesValidated": true,
  "lastCorporateActionDate": "2026-06-15",
  "lastSplitDate": "1998-06-02",
  "corporateActionHash": "sha256:2db9de897f0a97648320f58c89977fd03234c3bb71d62225f3cd4a8be06b02b2",
  "priceDataHash": "sha256:011d91693912d3014c8f6c8d226217d46ee2e1d71999f3638b86beb6192e3eae",
  "lastFullValidationAt": "2026-07-14T16:24:36Z",
  "updatedAt": "2026-07-14T16:24:36Z"
}
