{
  "ticker": "COF",
  "source": "yahoo",
  "firstDate": "1994-11-16",
  "lastDate": "2026-07-14",
  "records": 7945,
  "backfillCompleted": true,
  "adjustedSeriesValidated": true,
  "lastCorporateActionDate": "2026-05-19",
  "lastSplitDate": "1999-06-02",
  "corporateActionHash": "sha256:980079e9596fb4fa44b6bfaa4bd54f666d6126f7d9c555d69d6abe292374ea73",
  "priceDataHash": "sha256:deaee7f048c6b93d5a96274a1c5d317fef39250e5cd327e8d367a08b6bf578ca",
  "lastFullValidationAt": "2026-07-14T15:19:45Z",
  "updatedAt": "2026-07-15T04:19:36Z"
}
