{
  "ticker": "AVY",
  "source": "yahoo",
  "firstDate": "1973-02-21",
  "lastDate": "2026-07-13",
  "records": 13397,
  "backfillCompleted": true,
  "adjustedSeriesValidated": true,
  "lastCorporateActionDate": "2026-06-03",
  "lastSplitDate": "1996-12-23",
  "corporateActionHash": "sha256:aa277066874ed2901a01c7070a6d11696e135a33597756b285239478625d380d",
  "priceDataHash": "sha256:5dda4d0b38f36e30a1128084762dcc7d652e98ada5ee11337d2020844bdbba4a",
  "lastFullValidationAt": "2026-07-14T15:08:13Z",
  "updatedAt": "2026-07-14T15:08:13Z"
}
