{
  "ticker": "NOW",
  "source": "yahoo",
  "firstDate": "2012-06-29",
  "lastDate": "2026-07-22",
  "records": 3534,
  "backfillCompleted": true,
  "adjustedSeriesValidated": true,
  "lastCorporateActionDate": "2025-12-18",
  "lastSplitDate": "2025-12-18",
  "corporateActionHash": "sha256:a5afdb8dca9020fa9f4dae53cb17ca59b0e712b38b791327e8b2b6f81dc4e2a2",
  "priceDataHash": "sha256:edff024fa89595df6b9b386e32a541e8ccb1f758bed7a0ea9227d4142bf25fd7",
  "lastFullValidationAt": "2026-07-22T11:44:41Z",
  "updatedAt": "2026-07-23T11:30:36Z"
}
