{
  "ticker": "MGEE",
  "source": "yahoo",
  "firstDate": "1980-03-17",
  "lastDate": "2026-07-13",
  "records": 11510,
  "backfillCompleted": true,
  "adjustedSeriesValidated": true,
  "lastCorporateActionDate": "2026-06-01",
  "lastSplitDate": "2014-02-10",
  "corporateActionHash": "sha256:05885e96b51ad0177f4019b0df31d01aa68ef943307829279a635be9d16a274d",
  "priceDataHash": "sha256:5ae29887d15d8c5cc80e573004b2e98cdf4abc3b4aeee4e77b5b93c8571fb5b5",
  "lastFullValidationAt": "2026-07-14T16:43:32Z",
  "updatedAt": "2026-07-14T16:43:32Z"
}
