{
  "ticker": "CLOV",
  "source": "yahoo",
  "firstDate": "2020-06-12",
  "lastDate": "2026-07-08",
  "records": 1524,
  "backfillCompleted": true,
  "adjustedSeriesValidated": true,
  "lastCorporateActionDate": "",
  "lastSplitDate": "",
  "corporateActionHash": "sha256:e3b0c44298fc1c149afbf4c8996fb92427ae41e4649b934ca495991b7852b855",
  "priceDataHash": "sha256:f45dd5bd1bfdce9175004717b7156955d02950c51373c1ab67f10774ed21694e",
  "lastFullValidationAt": "2026-07-07T13:17:11Z",
  "updatedAt": "2026-07-09T05:09:26Z"
}
