{
  "ticker": "VNO",
  "source": "yahoo",
  "firstDate": "1980-03-17",
  "lastDate": "2026-07-16",
  "records": 11420,
  "backfillCompleted": true,
  "adjustedSeriesValidated": true,
  "lastCorporateActionDate": "2025-12-18",
  "lastSplitDate": "2017-07-18",
  "corporateActionHash": "sha256:8448ed1d58786007a03c2e23a67ba0899df02049e0230db272a2070ad10e0711",
  "priceDataHash": "sha256:4ad5b025502ab6a1ab5901e0dee5821e62fd4b54fd8b7edb2810d4304e74748b",
  "lastFullValidationAt": "2026-07-15T16:58:44Z",
  "updatedAt": "2026-07-17T11:06:22Z"
}
