{
  "ticker": "ADC",
  "source": "yahoo",
  "firstDate": "1994-04-15",
  "lastDate": "2026-07-13",
  "records": 8062,
  "backfillCompleted": true,
  "adjustedSeriesValidated": true,
  "lastCorporateActionDate": "2026-06-30",
  "lastSplitDate": "",
  "corporateActionHash": "sha256:3c798b0809dc003c41ee495b6ef4a8ee69b7c06fc865b22c630d25dd9f97dcbd",
  "priceDataHash": "sha256:4339f2ed0b45f5f8f0fdc6132e7ccce9f2cf5fbe6c0f6fe4cc5aa386c41dd083",
  "lastFullValidationAt": "2026-07-07T12:59:07Z",
  "updatedAt": "2026-07-14T04:01:07Z"
}
