{
  "ticker": "BG",
  "source": "yahoo",
  "firstDate": "2001-08-02",
  "lastDate": "2026-07-20",
  "records": 6270,
  "backfillCompleted": true,
  "adjustedSeriesValidated": true,
  "lastCorporateActionDate": "2026-05-22",
  "lastSplitDate": "",
  "corporateActionHash": "sha256:8665e8e586d104f9afb76d646a60228eb86da2c72012138d048cfdd4a46f069b",
  "priceDataHash": "sha256:cb6866f67795d9e4dffa9a71c162a7ab9ea264f88752605e64184a18c075ecb9",
  "lastFullValidationAt": "2026-07-14T15:11:01Z",
  "updatedAt": "2026-07-21T04:25:58Z"
}
