{
  "ticker": "MTZ",
  "source": "yahoo",
  "firstDate": "1973-02-21",
  "lastDate": "2026-07-23",
  "records": 13468,
  "backfillCompleted": true,
  "adjustedSeriesValidated": true,
  "lastCorporateActionDate": "2000-06-20",
  "lastSplitDate": "2000-06-20",
  "corporateActionHash": "sha256:bc92fb01e6d8abee4fb448533c1a97b8c775f0f138a51bbb6231949437fd8ee7",
  "priceDataHash": "sha256:cb04597bfb91d198ad3ee55e58a200ae20e7d641574efaa184c36bbb8b925849",
  "lastFullValidationAt": "2026-07-22T11:41:47Z",
  "updatedAt": "2026-07-24T15:14:25Z"
}
