{
  "ticker": "ALHC",
  "source": "yahoo",
  "firstDate": "2021-03-26",
  "lastDate": "2026-07-13",
  "records": 1329,
  "backfillCompleted": true,
  "adjustedSeriesValidated": true,
  "lastCorporateActionDate": "",
  "lastSplitDate": "",
  "corporateActionHash": "sha256:e3b0c44298fc1c149afbf4c8996fb92427ae41e4649b934ca495991b7852b855",
  "priceDataHash": "sha256:c359a5d5948aaf08da055191bdf08f9e32eecea7cfc867710f7538c39f9ae6bb",
  "lastFullValidationAt": "2026-07-14T15:03:01Z",
  "updatedAt": "2026-07-14T15:03:01Z"
}
