{
  "ticker": "BSX",
  "source": "yahoo",
  "firstDate": "1992-05-19",
  "lastDate": "2026-07-10",
  "records": 8595,
  "backfillCompleted": true,
  "adjustedSeriesValidated": true,
  "lastCorporateActionDate": "2003-11-06",
  "lastSplitDate": "2003-11-06",
  "corporateActionHash": "sha256:ce214fc83ce18277fccfeb0d67dbad26382e1f2f5abf5328386203e26ca271d7",
  "priceDataHash": "sha256:212aa3f54d3ebe2a7d486305f9c0bdfd238a332c3e306b44fda955f07b8e03bb",
  "lastFullValidationAt": "2026-07-07T13:12:03Z",
  "updatedAt": "2026-07-11T04:23:21Z"
}
