{
  "ticker": "IFF",
  "source": "yahoo",
  "firstDate": "1974-12-17",
  "lastDate": "2026-07-10",
  "records": 12850,
  "backfillCompleted": true,
  "adjustedSeriesValidated": true,
  "lastCorporateActionDate": "2026-06-18",
  "lastSplitDate": "1994-01-20",
  "corporateActionHash": "sha256:c1bdde90cfdcfbbb7ecef982cd2204ff8dbca5ed094a4827858b3955b52e9537",
  "priceDataHash": "sha256:1090b16d0306406e5138bbb8a641764b7e5f71bf64af4a8c5f1b6599214c97fc",
  "lastFullValidationAt": "2026-07-07T13:43:12Z",
  "updatedAt": "2026-07-11T07:23:28Z"
}
