{
  "ticker": "GRDN",
  "source": "yahoo",
  "firstDate": "2024-09-26",
  "lastDate": "2026-07-16",
  "records": 451,
  "backfillCompleted": true,
  "adjustedSeriesValidated": true,
  "lastCorporateActionDate": "",
  "lastSplitDate": "",
  "corporateActionHash": "sha256:e3b0c44298fc1c149afbf4c8996fb92427ae41e4649b934ca495991b7852b855",
  "priceDataHash": "sha256:39cdfe4e9eb9d257de6b7d83487227f45cd3c9ad4dfcff22c0372d77b8b76560",
  "lastFullValidationAt": "2026-07-14T16:27:12Z",
  "updatedAt": "2026-07-17T07:28:00Z"
}
