{
  "ticker": "CWK",
  "source": "yahoo",
  "firstDate": "2018-08-02",
  "lastDate": "2026-07-13",
  "records": 1995,
  "backfillCompleted": true,
  "adjustedSeriesValidated": true,
  "lastCorporateActionDate": "",
  "lastSplitDate": "",
  "corporateActionHash": "sha256:e3b0c44298fc1c149afbf4c8996fb92427ae41e4649b934ca495991b7852b855",
  "priceDataHash": "sha256:cf30867905f95eeb8c7f254562ce353a6dd5e2787a3309d6ce4c3b79e60f0c57",
  "lastFullValidationAt": "2026-07-14T15:23:41Z",
  "updatedAt": "2026-07-14T15:23:41Z"
}
