{
  "ticker": "ZION",
  "source": "yahoo",
  "firstDate": "1980-03-17",
  "lastDate": "2026-07-16",
  "records": 11556,
  "backfillCompleted": true,
  "adjustedSeriesValidated": true,
  "lastCorporateActionDate": "2026-05-14",
  "lastSplitDate": "1997-05-15",
  "corporateActionHash": "sha256:f68b7d585c9f68ec3771892271c235a7293c03f9bfc364c68da8ec556f3d7610",
  "priceDataHash": "sha256:4c539807481a116e640b4191aed3a11643f411c02f271be7f9118e87311daf20",
  "lastFullValidationAt": "2026-07-15T18:13:23Z",
  "updatedAt": "2026-07-17T12:17:41Z"
}
