{
  "ticker": "TWLO",
  "source": "yahoo",
  "firstDate": "2016-06-23",
  "lastDate": "2026-07-07",
  "records": 2522,
  "backfillCompleted": true,
  "adjustedSeriesValidated": true,
  "lastCorporateActionDate": "",
  "lastSplitDate": "",
  "corporateActionHash": "sha256:e3b0c44298fc1c149afbf4c8996fb92427ae41e4649b934ca495991b7852b855",
  "priceDataHash": "sha256:6ee58e3c33af534d0b46ebbc2defdf6973e1956f4a648622cb3c9bfaed28d3e5",
  "lastFullValidationAt": "2026-07-07T14:27:11Z",
  "updatedAt": "2026-07-08T11:20:28Z"
}
