{
  "ticker": "IONS",
  "source": "yahoo",
  "firstDate": "1991-05-17",
  "lastDate": "2026-07-16",
  "records": 8853,
  "backfillCompleted": true,
  "adjustedSeriesValidated": true,
  "lastCorporateActionDate": "",
  "lastSplitDate": "",
  "corporateActionHash": "sha256:e3b0c44298fc1c149afbf4c8996fb92427ae41e4649b934ca495991b7852b855",
  "priceDataHash": "sha256:d850cabadbdb07356f1a4ed150d661d138a5e1e636bb342a6fb056f8d1639a8c",
  "lastFullValidationAt": "2026-07-14T16:33:40Z",
  "updatedAt": "2026-07-17T07:31:24Z"
}
