{
  "ticker": "AYI",
  "source": "yahoo",
  "firstDate": "2001-12-03",
  "lastDate": "2026-07-09",
  "records": 6184,
  "backfillCompleted": true,
  "adjustedSeriesValidated": true,
  "lastCorporateActionDate": "2026-04-17",
  "lastSplitDate": "",
  "corporateActionHash": "sha256:7c61ba44c0cfb0d951cf1a228707b9d6ae30464179662cbae7c0ed63912d7b09",
  "priceDataHash": "sha256:556d3ce9b33dd5476330edb97e81920d57c245a3a70d12b15e311af97ed040d1",
  "lastFullValidationAt": "2026-07-07T13:07:23Z",
  "updatedAt": "2026-07-10T05:07:26Z"
}
