{
  "ticker": "BLBD",
  "source": "yahoo",
  "firstDate": "2014-03-20",
  "lastDate": "2026-07-14",
  "records": 3097,
  "backfillCompleted": true,
  "adjustedSeriesValidated": true,
  "lastCorporateActionDate": "",
  "lastSplitDate": "",
  "corporateActionHash": "sha256:e3b0c44298fc1c149afbf4c8996fb92427ae41e4649b934ca495991b7852b855",
  "priceDataHash": "sha256:f84f9622d9e1c3970ba68f2d3dab71b775ece73fc6a71c68f13717a0fd98d99c",
  "lastFullValidationAt": "2026-07-14T15:11:57Z",
  "updatedAt": "2026-07-15T04:15:36Z"
}
