{
  "ticker": "NNN",
  "source": "yahoo",
  "firstDate": "1984-10-09",
  "lastDate": "2026-07-22",
  "records": 10405,
  "backfillCompleted": true,
  "adjustedSeriesValidated": true,
  "lastCorporateActionDate": "2026-04-30",
  "lastSplitDate": "",
  "corporateActionHash": "sha256:96ba7f96c7e364a4b98e459ecbf0a457d46e2d6bcc821535493ceee287cde2b3",
  "priceDataHash": "sha256:179581e1da81a1fcc5984ae461ce196ff056bdf0b8fcf4e9191c4d5fcb1f4419",
  "lastFullValidationAt": "2026-07-22T11:44:23Z",
  "updatedAt": "2026-07-23T11:30:26Z"
}
