{
  "ticker": "ESTC",
  "source": "yahoo",
  "firstDate": "2018-10-05",
  "lastDate": "2026-07-17",
  "records": 1954,
  "backfillCompleted": true,
  "adjustedSeriesValidated": true,
  "lastCorporateActionDate": "",
  "lastSplitDate": "",
  "corporateActionHash": "sha256:e3b0c44298fc1c149afbf4c8996fb92427ae41e4649b934ca495991b7852b855",
  "priceDataHash": "sha256:c82c258de5ded74f28d124984fbcc2480e46b8573d2297520523e6f678a5ced0",
  "lastFullValidationAt": "2026-07-14T15:30:57Z",
  "updatedAt": "2026-07-18T04:18:28Z"
}
