{
  "ticker": "EQH",
  "source": "yahoo",
  "firstDate": "2018-05-10",
  "lastDate": "2026-07-14",
  "records": 2054,
  "backfillCompleted": true,
  "adjustedSeriesValidated": true,
  "lastCorporateActionDate": "2026-06-01",
  "lastSplitDate": "",
  "corporateActionHash": "sha256:7028a9a37bf2cfbebe6ca3f1b750cba5a83cdc32fb0ea8a9533847d95c6ce45a",
  "priceDataHash": "sha256:bceee1a6653fa634ff78aef92a3c2cb2b1fe25f3b92ab974b69fd3be6c0bd880",
  "lastFullValidationAt": "2026-07-14T15:30:09Z",
  "updatedAt": "2026-07-15T04:24:50Z"
}
