{
  "ticker": "POST",
  "source": "yahoo",
  "firstDate": "2012-01-27",
  "lastDate": "2026-07-08",
  "records": 3631,
  "backfillCompleted": true,
  "adjustedSeriesValidated": true,
  "lastCorporateActionDate": "2022-03-11",
  "lastSplitDate": "2022-03-11",
  "corporateActionHash": "sha256:ab73861aaed9ea4269f653ad3a35ff9666298d6d632450d0ed2c6f217d944a72",
  "priceDataHash": "sha256:0670f765c74d3fc3588f1a468b5ed7ff66010444e4243779acd8563f74658002",
  "lastFullValidationAt": "2026-07-07T14:09:19Z",
  "updatedAt": "2026-07-09T12:10:22Z"
}
