{
  "ticker": "VC",
  "source": "yahoo",
  "firstDate": "2010-10-05",
  "lastDate": "2026-07-09",
  "records": 3962,
  "backfillCompleted": true,
  "adjustedSeriesValidated": true,
  "lastCorporateActionDate": "2026-03-02",
  "lastSplitDate": "",
  "corporateActionHash": "sha256:285291131d07c8389b334aabecf8c7186791d7015965f048ab8af62bdb82f247",
  "priceDataHash": "sha256:d612fd590b5916ea3095e43f730c1994ce7df917f25c9eae192f9a4854c9e9bc",
  "lastFullValidationAt": "2026-07-07T14:29:59Z",
  "updatedAt": "2026-07-10T12:12:31Z"
}
