{
  "ticker": "MA",
  "source": "yahoo",
  "firstDate": "2006-05-25",
  "lastDate": "2026-07-10",
  "records": 5062,
  "backfillCompleted": true,
  "adjustedSeriesValidated": true,
  "lastCorporateActionDate": "2026-07-09",
  "lastSplitDate": "2014-01-22",
  "corporateActionHash": "sha256:682b230808e7019e8136874cee9f5bb0ec07ebb3cef9c5a86318cc87332a94d8",
  "priceDataHash": "sha256:fb4dbbbe15a017c109f43547df9712a5b947eb53e5f92e0f7aa7206391ab5e15",
  "lastFullValidationAt": "2026-07-07T13:52:03Z",
  "updatedAt": "2026-07-11T07:27:54Z"
}
