{
  "ticker": "APP",
  "source": "yahoo",
  "firstDate": "2021-04-15",
  "lastDate": "2026-07-21",
  "records": 1322,
  "backfillCompleted": true,
  "adjustedSeriesValidated": true,
  "lastCorporateActionDate": "",
  "lastSplitDate": "",
  "corporateActionHash": "sha256:e3b0c44298fc1c149afbf4c8996fb92427ae41e4649b934ca495991b7852b855",
  "priceDataHash": "sha256:e1ea977af3c2abc097009a44a6abf7d5613e127210abee84a82245c07e502fb2",
  "lastFullValidationAt": "2026-07-22T04:28:14Z",
  "updatedAt": "2026-07-22T04:28:14Z"
}
