{
  "ticker": "TGT",
  "source": "yahoo",
  "firstDate": "1973-02-21",
  "lastDate": "2026-07-20",
  "records": 13415,
  "backfillCompleted": true,
  "adjustedSeriesValidated": true,
  "lastCorporateActionDate": "2026-05-13",
  "lastSplitDate": "2000-07-20",
  "corporateActionHash": "sha256:df057ea51a61d4191169f60cea10af0b4205b70e962592c426467b81b5d3596e",
  "priceDataHash": "sha256:58f6fee381c89c90a5b42f9c69a43cfe3d23b1fb837cb682d7578c917345533c",
  "lastFullValidationAt": "2026-07-15T16:51:38Z",
  "updatedAt": "2026-07-21T15:22:48Z"
}
