{
  "ticker": "OBDC",
  "source": "yahoo",
  "firstDate": "2019-07-18",
  "lastDate": "2026-07-13",
  "records": 1749,
  "backfillCompleted": true,
  "adjustedSeriesValidated": true,
  "lastCorporateActionDate": "2026-06-30",
  "lastSplitDate": "",
  "corporateActionHash": "sha256:eb6e255674c8c2138feb95529c254d32f20c827824ed2c6280369ab8e7eeb286",
  "priceDataHash": "sha256:1a9bae82ed2d3c5f6a84b58daf47035beb34496a8ffd2c7b17de5e208104ebb4",
  "lastFullValidationAt": "2026-07-14T16:52:15Z",
  "updatedAt": "2026-07-14T16:52:15Z"
}
