{
  "ticker": "ADBE",
  "source": "yahoo",
  "firstDate": "1986-08-13",
  "lastDate": "2026-07-09",
  "records": 10052,
  "backfillCompleted": true,
  "adjustedSeriesValidated": true,
  "lastCorporateActionDate": "2005-05-24",
  "lastSplitDate": "2005-05-24",
  "corporateActionHash": "sha256:fe2714f620900705d494619563e990a22ba9dc55f94459b164f57bdbf085d61f",
  "priceDataHash": "sha256:119261c68dd98b18d9ee1c506b9a751148bbb644da97312913353a70eff5ebe4",
  "lastFullValidationAt": "2026-07-07T12:59:03Z",
  "updatedAt": "2026-07-10T05:03:12Z"
}
