{
  "ticker": "SUN",
  "source": "yahoo",
  "firstDate": "2012-09-20",
  "lastDate": "2026-07-14",
  "records": 3470,
  "backfillCompleted": true,
  "adjustedSeriesValidated": true,
  "lastCorporateActionDate": "2026-05-08",
  "lastSplitDate": "",
  "corporateActionHash": "sha256:ac7f64cf56a72d7599ad0e94d7846a1ac2399d258ab8c0a0e4678f6d5321fecd",
  "priceDataHash": "sha256:e21127e3adfabc75387660fe858d5f6ab8d70b8449e48de1ed6eac3750c9a628",
  "lastFullValidationAt": "2026-07-15T16:49:30Z",
  "updatedAt": "2026-07-15T16:49:30Z"
}
