{
  "ticker": "GPI",
  "source": "yahoo",
  "firstDate": "1997-10-30",
  "lastDate": "2026-07-20",
  "records": 7219,
  "backfillCompleted": true,
  "adjustedSeriesValidated": true,
  "lastCorporateActionDate": "2026-06-01",
  "lastSplitDate": "",
  "corporateActionHash": "sha256:d5a6d1a3be7fe2e6f4abe722dec42c78539978816207f281c1861aeede247807",
  "priceDataHash": "sha256:712aa43bb036937dcc3e6fac41f95b2dfffebfd2b1665a3f6e85fbe8db4f8b4e",
  "lastFullValidationAt": "2026-07-14T16:26:52Z",
  "updatedAt": "2026-07-21T11:17:29Z"
}
