{
  "ticker": "TRV",
  "source": "yahoo",
  "firstDate": "1975-11-17",
  "lastDate": "2026-07-17",
  "records": 12676,
  "backfillCompleted": true,
  "adjustedSeriesValidated": true,
  "lastCorporateActionDate": "2026-06-10",
  "lastSplitDate": "1998-05-12",
  "corporateActionHash": "sha256:0cc45b50590c60315a7cc05395a6d305abefac0984014c00c5ea89fcc73c8815",
  "priceDataHash": "sha256:3d0335a783f58fe1b2b9606c8cde31990af4d4abb7a14e88418260e745fc31f7",
  "lastFullValidationAt": "2026-07-15T16:53:38Z",
  "updatedAt": "2026-07-18T10:37:51Z"
}
