{
  "ticker": "LAD",
  "source": "yahoo",
  "firstDate": "1996-12-18",
  "lastDate": "2026-07-15",
  "records": 7423,
  "backfillCompleted": true,
  "adjustedSeriesValidated": true,
  "lastCorporateActionDate": "2026-05-08",
  "lastSplitDate": "",
  "corporateActionHash": "sha256:f3a790cf811cb02d1dedb7a2b0ef2b224a4c5f32444bca03a0dbc84c147b1bbd",
  "priceDataHash": "sha256:d8842a39c2ebd249514d035be256e8bd94f74006171b6406a9f281ed39342702",
  "lastFullValidationAt": "2026-07-14T16:37:48Z",
  "updatedAt": "2026-07-16T07:37:49Z"
}
