{
  "ticker": "SPGI",
  "source": "yahoo",
  "firstDate": "1973-02-21",
  "lastDate": "2026-07-15",
  "records": 13397,
  "backfillCompleted": true,
  "adjustedSeriesValidated": true,
  "lastCorporateActionDate": "2026-07-01",
  "lastSplitDate": "2026-07-01",
  "corporateActionHash": "sha256:13fc376a8722b5e910d8d7bbb8e7f4c4e6c48f68da5f747d0c6049d075a77063",
  "priceDataHash": "sha256:a5274d593ddae0f27d7d19bf056b4ac0edc8ca8d04000ad3e89d3c7c618cb47e",
  "lastFullValidationAt": "2026-07-15T16:47:58Z",
  "updatedAt": "2026-07-16T11:13:53Z"
}
