{
  "ticker": "FLG",
  "source": "yahoo",
  "firstDate": "1993-11-23",
  "lastDate": "2026-07-21",
  "records": 8181,
  "backfillCompleted": true,
  "adjustedSeriesValidated": true,
  "lastCorporateActionDate": "2026-06-05",
  "lastSplitDate": "2024-07-12",
  "corporateActionHash": "sha256:376d2219770f0cb053371ce7d535065371e8d0769fcfba0df905a59b969b5222",
  "priceDataHash": "sha256:ff15f46eeaefd633b52e2bef09b1e2d4c34a7c4947ff4fbcfd5fd4bad2008c8a",
  "lastFullValidationAt": "2026-07-22T11:16:21Z",
  "updatedAt": "2026-07-22T11:16:21Z"
}
