{
  "ticker": "DYN",
  "source": "yahoo",
  "firstDate": "2020-09-17",
  "lastDate": "2026-07-15",
  "records": 1462,
  "backfillCompleted": true,
  "adjustedSeriesValidated": true,
  "lastCorporateActionDate": "",
  "lastSplitDate": "",
  "corporateActionHash": "sha256:e3b0c44298fc1c149afbf4c8996fb92427ae41e4649b934ca495991b7852b855",
  "priceDataHash": "sha256:443f9e951f8e1dc7b0b8b2b5cf9a8d29733cb747fccc4e515fa1a8194858f9f5",
  "lastFullValidationAt": "2026-07-14T15:27:53Z",
  "updatedAt": "2026-07-16T04:27:20Z"
}
