{
  "ticker": "LNT",
  "source": "yahoo",
  "firstDate": "1973-02-21",
  "lastDate": "2026-07-10",
  "records": 13169,
  "backfillCompleted": true,
  "adjustedSeriesValidated": true,
  "lastCorporateActionDate": "2026-04-30",
  "lastSplitDate": "2016-05-20",
  "corporateActionHash": "sha256:d4238e9a279cbe6195566f67b848d5f7d53fb417792749bf100fd786b39c2bfe",
  "priceDataHash": "sha256:e7cfd0f4c75c69de8ec8d1a329e5b179d11a94bf21b5df6f6f16b34a97c2560f",
  "lastFullValidationAt": "2026-07-07T13:50:31Z",
  "updatedAt": "2026-07-11T07:27:08Z"
}
