{
  "ticker": "PBLS",
  "source": "yahoo",
  "firstDate": "2026-06-10",
  "lastDate": "2026-07-23",
  "records": 30,
  "backfillCompleted": true,
  "adjustedSeriesValidated": true,
  "lastCorporateActionDate": "",
  "lastSplitDate": "",
  "corporateActionHash": "sha256:e3b0c44298fc1c149afbf4c8996fb92427ae41e4649b934ca495991b7852b855",
  "priceDataHash": "sha256:6026021b5a97521fd0073f25b388e2f694d24c0a03bdf355963529178fb2dc02",
  "lastFullValidationAt": "2026-07-23T15:17:47Z",
  "updatedAt": "2026-07-24T16:55:41Z"
}
